pre_request/__init__.py
pre_request/__version__.py
pre_request/exception.py
pre_request/macro.py
pre_request/regexp.py
pre_request/request.py
pre_request/response.py
pre_request/rules.py
pre_request/utils.py
pre_request/filters/__init__.py
pre_request/filters/base.py
pre_request/filters/cross/__init__.py
pre_request/filters/cross/equal_key.py
pre_request/filters/cross/required_with.py
pre_request/filters/simple/__init__.py
pre_request/filters/simple/content.py
pre_request/filters/simple/default.py
pre_request/filters/simple/empty.py
pre_request/filters/simple/enum.py
pre_request/filters/simple/equal.py
pre_request/filters/simple/json.py
pre_request/filters/simple/length.py
pre_request/filters/simple/multi.py
pre_request/filters/simple/network.py
pre_request/filters/simple/range.py
pre_request/filters/simple/regexp.py
pre_request/filters/simple/split.py
pre_request/filters/simple/string.py
pre_request/filters/simple/trim.py
pre_request/filters/simple/type.py
pre_request-2.1.5.dist-info/LICENSE
pre_request-2.1.5.dist-info/METADATA
pre_request-2.1.5.dist-info/WHEEL
pre_request-2.1.5.dist-info/top_level.txt
pre_request-2.1.5.dist-info/RECORD
